{
	"textures": [
		{
			"image": "40120.png",
			"format": "RGBA8888",
			"size": {
				"w": 466,
				"h": 9503
			},
			"scale": 1,
			"frames": [
				{
					"filename": "1",
					"rotated": false,
					"trimmed": false,
					"sourceSize": {
						"w": 464,
						"h": 557
					},
					"spriteSourceSize": {
						"x": 0,
						"y": 0,
						"w": 464,
						"h": 557
					},
					"frame": {
						"x": 1,
						"y": 1,
						"w": 464,
						"h": 557
					}
				},
				{
					"filename": "2",
					"rotated": false,
					"trimmed": false,
					"sourceSize": {
						"w": 464,
						"h": 557
					},
					"spriteSourceSize": {
						"x": 0,
						"y": 0,
						"w": 464,
						"h": 557
					},
					"frame": {
						"x": 1,
						"y": 560,
						"w": 464,
						"h": 557
					}
				},
				{
					"filename": "18",
					"rotated": false,
					"trimmed": false,
					"sourceSize": {
						"w": 464,
						"h": 557
					},
					"spriteSourceSize": {
						"x": 0,
						"y": 0,
						"w": 464,
						"h": 557
					},
					"frame": {
						"x": 1,
						"y": 560,
						"w": 464,
						"h": 557
					}
				},
				{
					"filename": "3",
					"rotated": false,
					"trimmed": false,
					"sourceSize": {
						"w": 464,
						"h": 557
					},
					"spriteSourceSize": {
						"x": 0,
						"y": 0,
						"w": 464,
						"h": 557
					},
					"frame": {
						"x": 1,
						"y": 1119,
						"w": 464,
						"h": 557
					}
				},
				{
					"filename": "4",
					"rotated": false,
					"trimmed": false,
					"sourceSize": {
						"w": 464,
						"h": 557
					},
					"spriteSourceSize": {
						"x": 0,
						"y": 0,
						"w": 464,
						"h": 557
					},
					"frame": {
						"x": 1,
						"y": 1678,
						"w": 464,
						"h": 557
					}
				},
				{
					"filename": "5",
					"rotated": false,
					"trimmed": false,
					"sourceSize": {
						"w": 464,
						"h": 557
					},
					"spriteSourceSize": {
						"x": 0,
						"y": 0,
						"w": 464,
						"h": 557
					},
					"frame": {
						"x": 1,
						"y": 2237,
						"w": 464,
						"h": 557
					}
				},
				{
					"filename": "6",
					"rotated": false,
					"trimmed": false,
					"sourceSize": {
						"w": 464,
						"h": 557
					},
					"spriteSourceSize": {
						"x": 0,
						"y": 0,
						"w": 464,
						"h": 557
					},
					"frame": {
						"x": 1,
						"y": 2796,
						"w": 464,
						"h": 557
					}
				},
				{
					"filename": "7",
					"rotated": false,
					"trimmed": false,
					"sourceSize": {
						"w": 464,
						"h": 557
					},
					"spriteSourceSize": {
						"x": 0,
						"y": 0,
						"w": 464,
						"h": 557
					},
					"frame": {
						"x": 1,
						"y": 3355,
						"w": 464,
						"h": 557
					}
				},
				{
					"filename": "8",
					"rotated": false,
					"trimmed": false,
					"sourceSize": {
						"w": 464,
						"h": 557
					},
					"spriteSourceSize": {
						"x": 0,
						"y": 0,
						"w": 464,
						"h": 557
					},
					"frame": {
						"x": 1,
						"y": 3914,
						"w": 464,
						"h": 557
					}
				},
				{
					"filename": "9",
					"rotated": false,
					"trimmed": false,
					"sourceSize": {
						"w": 464,
						"h": 557
					},
					"spriteSourceSize": {
						"x": 0,
						"y": 0,
						"w": 464,
						"h": 557
					},
					"frame": {
						"x": 1,
						"y": 4473,
						"w": 464,
						"h": 557
					}
				},
				{
					"filename": "10",
					"rotated": false,
					"trimmed": false,
					"sourceSize": {
						"w": 464,
						"h": 557
					},
					"spriteSourceSize": {
						"x": 0,
						"y": 0,
						"w": 464,
						"h": 557
					},
					"frame": {
						"x": 1,
						"y": 5032,
						"w": 464,
						"h": 557
					}
				},
				{
					"filename": "11",
					"rotated": false,
					"trimmed": false,
					"sourceSize": {
						"w": 464,
						"h": 557
					},
					"spriteSourceSize": {
						"x": 0,
						"y": 0,
						"w": 464,
						"h": 557
					},
					"frame": {
						"x": 1,
						"y": 5591,
						"w": 464,
						"h": 557
					}
				},
				{
					"filename": "12",
					"rotated": false,
					"trimmed": false,
					"sourceSize": {
						"w": 464,
						"h": 557
					},
					"spriteSourceSize": {
						"x": 0,
						"y": 0,
						"w": 464,
						"h": 557
					},
					"frame": {
						"x": 1,
						"y": 6150,
						"w": 464,
						"h": 557
					}
				},
				{
					"filename": "13",
					"rotated": false,
					"trimmed": false,
					"sourceSize": {
						"w": 464,
						"h": 557
					},
					"spriteSourceSize": {
						"x": 0,
						"y": 0,
						"w": 464,
						"h": 557
					},
					"frame": {
						"x": 1,
						"y": 6709,
						"w": 464,
						"h": 557
					}
				},
				{
					"filename": "14",
					"rotated": false,
					"trimmed": false,
					"sourceSize": {
						"w": 464,
						"h": 557
					},
					"spriteSourceSize": {
						"x": 0,
						"y": 0,
						"w": 464,
						"h": 557
					},
					"frame": {
						"x": 1,
						"y": 7268,
						"w": 464,
						"h": 557
					}
				},
				{
					"filename": "15",
					"rotated": false,
					"trimmed": false,
					"sourceSize": {
						"w": 464,
						"h": 557
					},
					"spriteSourceSize": {
						"x": 0,
						"y": 0,
						"w": 464,
						"h": 557
					},
					"frame": {
						"x": 1,
						"y": 7827,
						"w": 464,
						"h": 557
					}
				},
				{
					"filename": "16",
					"rotated": false,
					"trimmed": false,
					"sourceSize": {
						"w": 464,
						"h": 557
					},
					"spriteSourceSize": {
						"x": 0,
						"y": 0,
						"w": 464,
						"h": 557
					},
					"frame": {
						"x": 1,
						"y": 8386,
						"w": 464,
						"h": 557
					}
				},
				{
					"filename": "17",
					"rotated": false,
					"trimmed": false,
					"sourceSize": {
						"w": 464,
						"h": 557
					},
					"spriteSourceSize": {
						"x": 0,
						"y": 0,
						"w": 464,
						"h": 557
					},
					"frame": {
						"x": 1,
						"y": 8945,
						"w": 464,
						"h": 557
					}
				}
			]
		}
	],
	"meta": {
		"app": "https://www.codeandweb.com/texturepacker",
		"version": "3.0",
		"smartupdate": "$TexturePacker:SmartUpdate:2cf479bea574258e0c19e86b315d6d42:6f5d0349000024beff8cfd119aae66f7:5d4b6864684bc48387365e911f120a44$"
	}
}
